MANIFEST.in
README.md
setup.py
src/phosphoprotools/__init__.py
src/phosphoprotools/piscoreanalysis.py
src/phosphoprotools/preprocessing.py
src/phosphoprotools/pubfetch.py
src/phosphoprotools/siteannotation.py
src/phosphoprotools/synonymsfetch.py
src/phosphoprotools.egg-info/PKG-INFO
src/phosphoprotools.egg-info/SOURCES.txt
src/phosphoprotools.egg-info/dependency_links.txt
src/phosphoprotools.egg-info/not-zip-safe
src/phosphoprotools.egg-info/requires.txt
src/phosphoprotools.egg-info/top_level.txt
src/phosphoprotools/data/Phosphorylation_site_dataset.pickle
src/phosphoprotools/data/Phosphosite_seq.fasta.pickle
src/phosphoprotools/data/Regulatory_sites.pickle
src/phosphoprotools/data/__init__.py
src/phosphoprotools/data/refdbprocessing.py
src/phosphoprotools/data/saved_synonyms.pickle