Metadata-Version: 1.1
Name: phosphoprotools
Version: 0.19
Summary: Tools for phosphoproteomics data analysis
Home-page: https://github.com/ThomasHSmith/phosphoprotools
Author: Thomas H. Smith
Author-email: ThomasHoraceSmith@gmail.com
License: MIT
Platform: UNKNOWN
Classifier: Development Status :: 3 - Alpha
Classifier: License :: OSI Approved :: MIT License
Classifier: Programming Language :: Python :: 2.7
